vgd_reader/__init__.py
vgd_reader/parser.py
vgd_reader-0.1.0.dist-info/licenses/LICENSE
vgd_reader-0.1.0.dist-info/METADATA
vgd_reader-0.1.0.dist-info/WHEEL
vgd_reader-0.1.0.dist-info/top_level.txt
vgd_reader-0.1.0.dist-info/RECORD
