Metadata-Version: 2.4
Name: vgd-reader
Version: 0.1.0
Summary: Parse Thermo Scientific VGD files for XPS (X-ray Photoelectron Spectroscopy) analysis
Author-email: Gwilherm Kerherve <g.kerherve@imperial.ac.uk>
License: MIT
Project-URL: Homepage, https://github.com/gkerherve/vgd_reader
Project-URL: Documentation, https://github.com/gkerherve/vgd_reader#readme
Project-URL: Repository, https://github.com/gkerherve/vgd_reader
Keywords: xps,spectroscopy,thermo,vgd,surface-analysis,photoelectron
Classifier: Development Status :: 4 - Beta
Classifier: Intended Audience :: Science/Research
Classifier: License :: OSI Approved :: MIT License
Classifier: Operating System :: OS Independent
Classifier: Programming Language :: Python :: 3
Classifier: Programming Language :: Python :: 3.8
Classifier: Programming Language :: Python :: 3.9
Classifier: Programming Language :: Python :: 3.10
Classifier: Programming Language :: Python :: 3.11
Classifier: Programming Language :: Python :: 3.12
Classifier: Topic :: Scientific/Engineering :: Chemistry
Classifier: Topic :: Scientific/Engineering :: Physics
Requires-Python: >=3.8
License-File: LICENSE
Requires-Dist: numpy>=1.20.0
Requires-Dist: olefile>=0.46
Provides-Extra: excel
Requires-Dist: openpyxl>=3.0.0; extra == "excel"
Provides-Extra: pandas
Requires-Dist: pandas>=1.3.0; extra == "pandas"
Provides-Extra: all
Requires-Dist: openpyxl>=3.0.0; extra == "all"
Requires-Dist: pandas>=1.3.0; extra == "all"
Provides-Extra: dev
Requires-Dist: pytest>=7.0.0; extra == "dev"
Requires-Dist: pytest-cov>=4.0.0; extra == "dev"
Requires-Dist: black>=23.0.0; extra == "dev"
Requires-Dist: ruff>=0.1.0; extra == "dev"
Dynamic: license-file
